itk_meshtopolydata.libs/libtbb-3c88584c.so.12.9
itk/itkPolyDataPython.py
itk/itkMeshToPolyDataFilterPython.py
itk/itkPolyDataToMeshFilterPython.py
itk/_MeshToPolyDataPython.so
itk/itkImageToPointSetFilterPython.py
itk/MeshToPolyDataPython.py
itk/Configuration/MeshToPolyData_snake_case.py
itk/Configuration/MeshToPolyDataConfig.py
itk_meshtopolydata-0.11.1.dist-info/METADATA
itk_meshtopolydata-0.11.1.dist-info/RECORD
itk_meshtopolydata-0.11.1.dist-info/WHEEL
itk_meshtopolydata-0.11.1.dist-info/licenses/LICENSE
